bytesize/__init__.py
bytesize/bytesize.py
bytesize/byteunit.py
bytesize/py.typed
pybytesize-0.8.1.dist-info/METADATA
pybytesize-0.8.1.dist-info/WHEEL
pybytesize-0.8.1.dist-info/licenses/LICENSE
pybytesize-0.8.1.dist-info/RECORD
