Metadata-Version: 2.4
Name: pybytesize
Version: 0.8.1
Summary: Smart, Pythonic, and dynamic: automatic unit selection and conversions made intuitive.
Project-URL: homepage, https://github.com/jjjermiah/ByteSize
Project-URL: repository, https://github.com/jjjermiah/ByteSize
Project-URL: documentation, https://jjjermiah.github.io/PyByteSize/
Project-URL: changelog, https://github.com/jjjermiah/ByteSize/blob/main/docs/CHANGELOG.md
Project-URL: issues, https://github.com/jjjermiah/ByteSize/issues
Author-email: Jermiah Joseph <jermiahjoseph98@gmail.com>
Maintainer-email: Jermiah Joseph <jermiahjoseph98@gmail.com>
License-Expression: MIT
License-File: LICENSE
Keywords: bytesize,pixi,python
Classifier: Development Status :: 1 - Planning
Classifier: License :: OSI Approved :: MIT License
Classifier: Operating System :: OS Independent
Classifier: Programming Language :: Python :: 3
Classifier: Programming Language :: Python :: 3.10
Classifier: Programming Language :: Python :: 3.11
Classifier: Programming Language :: Python :: 3.12
Classifier: Programming Language :: Python :: 3.13
Requires-Python: >=3.10
